{
  "name": "shell_exec",
  "description": "Execute shell commands and return the output. SECURITY WARNING: Only use with trusted commands.",
  "parameters": {
    "type": "object",
    "properties": {
      "command": {
        "type": "string",
        "description": "The shell command to execute"
      },
      "cwd": {
        "type": "string",
        "description": "Working directory for command execution (optional)"
      },
      "timeout": {
        "type": "number",
        "description": "Timeout in milliseconds (default: 30000)"
      }
    },
    "required": ["command"]
  },
  "handler": "async (args) => { const { command, cwd, timeout = 30000 } = args; const cp = await import('child_process'); const execSync = cp.execSync; try { const output = execSync(command, { cwd: cwd || process.cwd(), timeout, encoding: 'utf-8', maxBuffer: 10 * 1024 * 1024 }); return { success: true, output: output.trim(), command }; } catch (error) { return { success: false, error: error.message, stderr: error.stderr ? error.stderr.toString() : '', command }; } }"
}
